LICENSE.md
README.md
setup.py
OKD/__init__.py
OKD.egg-info/PKG-INFO
OKD.egg-info/SOURCES.txt
OKD.egg-info/dependency_links.txt
OKD.egg-info/requires.txt
OKD.egg-info/top_level.txt