Metadata-Version: 2.1
Name: OKD
Version: 0.0.4
Summary: Online Knee Detection Model
Home-page: https://github.com/harish2sista/OKD
Author: Harish Sita
Author-email: hsista@stevens.edu
License: BSD 3-Clause License
Project-URL: Bug Tracker, https://github.com/harish2sista/OKD/issues
Platform: UNKNOWN
License-File: LICENSE.md
